django_pyowm/__init__.py
django_pyowm/models.py
django_pyowm/tests.py
django_pyowm/migrations/__init__.py
django_pyowm-0.1.0.dist-info/DESCRIPTION.rst
django_pyowm-0.1.0.dist-info/METADATA
django_pyowm-0.1.0.dist-info/RECORD
django_pyowm-0.1.0.dist-info/WHEEL
django_pyowm-0.1.0.dist-info/metadata.json
django_pyowm-0.1.0.dist-info/top_level.txt
