Metadata-Version: 2.0
Name: django-pyowm
Version: 0.1.0
Summary: A Django ORM interface to operate with PyOWM domain entities
Home-page: https://github.com/csparpa/django_pyowm
Author: Claudio Sparpaglione
Author-email: csparpa@gmail.com
License: MIT License
Platform: UNKNOWN
Classifier: Environment :: Web Environment
Classifier: Framework :: Django
Classifier: Framework :: Django :: 1.10
Classifier: Intended Audience :: Developers
Classifier: License :: OSI Approved :: MIT License
Classifier: Operating System :: OS Independent
Classifier: Programming Language :: Python
Classifier: Programming Language :: Python :: 2
Classifier: Programming Language :: Python :: 3.2
Classifier: Programming Language :: Python :: 3.3
Classifier: Programming Language :: Python :: 3.4
Classifier: Programming Language :: Python :: 3.5
Classifier: Topic :: Internet :: WWW/HTTP
Classifier: Topic :: Internet :: WWW/HTTP :: Dynamic Content
Requires-Dist: Django (>=1.10.3,<2)
Requires-Dist: pyowm (>=2.5.0,<3)
